setup.py
onemg_excel_csv/__init__.py
onemg_excel_csv/excel_csv_reader.py
onemg_excel_csv.egg-info/PKG-INFO
onemg_excel_csv.egg-info/SOURCES.txt
onemg_excel_csv.egg-info/dependency_links.txt
onemg_excel_csv.egg-info/requires.txt
onemg_excel_csv.egg-info/top_level.txt