Metadata-Version: 1.0
Name: onemg-excel-csv
Version: 1.0.0
Summary: onemg_excel_csv library which uses 
Home-page: UNKNOWN
Author: Om Jangir
Author-email: omjangir2006@gmail.com
License: UNKNOWN
Platform: UNKNOWN
